ceo/__init__.py
ceo/ability/__init__.py
ceo/ability/ability.py
ceo/ability/agentic_ability.py
ceo/ability/base_ability.py
ceo/ability/mcp_ability.py
ceo/ability/mcp_agentic_ability.py
ceo/brain/__init__.py
ceo/brain/agent.py
ceo/brain/base_agent.py
ceo/brain/mcp_agent.py
ceo/brain/memory_augment.py
ceo/brain/hook/__init__.py
ceo/brain/hook/after_action_taken.py
ceo/brain/hook/base_hook.py
ceo/brain/hook/before_action_taken.py
ceo/brain/lm/__init__.py
ceo/brain/lm/dashscope.py
ceo/brain/lm/deepseek.py
ceo/brain/lm/openai.py
ceo/enum/Personality.py
ceo/enum/__init__.py
ceo/exception/__init__.py
ceo/exception/invalid_mcp_tool_exception.py
ceo/exception/not_a_regular_function_exception.py
ceo/exception/null_request_exception.py
ceo/exception/too_dumb_exception.py
ceo/message/__init__.py
ceo/message/after_action_taken_message.py
ceo/message/all_done_message.py
ceo/message/base_massage.py
ceo/message/before_action_taken_message.py
ceo/prompt/__init__.py
ceo/prompt/analyser_prompt.py
ceo/prompt/docstring_prompt.py
ceo/prompt/executor_prompt.py
ceo/prompt/introspection_prompt.py
ceo/prompt/next_move_prompt.py
ceo/prompt/prompt.py
ceo/prompt/request_resolver_prompt.py
ceo/prompt/scheduler_prompt.py
ceo/prompt/self_introduce.py
ceo/util/__init__.py
ceo/util/ability.py
ceo/util/agentic.py
ceo/util/mcp_session.py
ceo/util/synchronized_call.py
ceo_py-0.13.1.dist-info/licenses/LICENSE
ceo_py-0.13.1.dist-info/METADATA
ceo_py-0.13.1.dist-info/WHEEL
ceo_py-0.13.1.dist-info/top_level.txt
ceo_py-0.13.1.dist-info/RECORD
